[{"date": "04-25-2024", "type": "Environmental Complaint", "seats": "Food Processor Retail - In-State", "reportUrl": "https://ri.healthinspections.us/_templates/62/Restaurant/_report_full.cfm?inspID=4162841&domainID=62&userID=0&rtype=Restaurant&reportIDParent=0&SubType='&dsn=DHD_62&wguid=1367&wgunm=sysuser&wgdmn=630_2&logintime=%2200:00:00%20AM%22&public=1", "violations": [{"item": 55, "code": "6-501.11", "severity": "C", "text": "At the time of inspection, the ceiling support grid over the dish area was observed to have a loosely attached, hanging piece exposing the structure area above. The physical facilities must be maintained in good repair and maintained to aid in the current pest control program. New Violation. Correct By: 04/25/2024"}]}]