[{"date": "05-16-2025", "type": "Routine", "seats": "Food Processor Wholesale - In-State", "reportUrl": "https://ri.healthinspections.us/_templates/62/Restaurant/_report_full.cfm?inspID=5601110&domainID=62&userID=0&rtype=Restaurant&reportIDParent=0&SubType='&dsn=DHD_62&wguid=1367&wgunm=sysuser&wgdmn=630_2&logintime=%2200:00:00%20AM%22&public=1", "violations": [{"item": 49, "code": "4-601.11(B)", "severity": "C", "text": "The non-food contact surfaces of the baking sheets on the lower shelving in the kitchen (used to store equipment) have an accumulation of dust, dirt, food residue, and other debris. Baking sheets to be cleaned and sanitized). New Violation. Correct By: 05/30/2025"}]}]